odoo/addons/sale_blanket_order_fiscal/LICENSE
odoo/addons/sale_blanket_order_fiscal/README.rst
odoo/addons/sale_blanket_order_fiscal/__init__.py
odoo/addons/sale_blanket_order_fiscal/__manifest__.py
odoo/addons/sale_blanket_order_fiscal/images/screen.png
odoo/addons/sale_blanket_order_fiscal/static/description/icon.png
odoo/addons/sale_blanket_order_fiscal/static/description/index.html
odoo/addons/sale_blanket_order_fiscal/tests/TEST_INSTRUCTIONS.rst
odoo/addons/sale_blanket_order_fiscal/views/blanket_order.xml
odoo/addons/sale_blanket_order_fiscal/wizard/__init__.py
odoo/addons/sale_blanket_order_fiscal/wizard/create_sale_orders.py
odoo_addon_sale_blanket_order_fiscal-16.0.1.0.0.dist-info/METADATA
odoo_addon_sale_blanket_order_fiscal-16.0.1.0.0.dist-info/WHEEL
odoo_addon_sale_blanket_order_fiscal-16.0.1.0.0.dist-info/top_level.txt
odoo_addon_sale_blanket_order_fiscal-16.0.1.0.0.dist-info/RECORD
